ismslib/__init__.py
ismslib/isms.py
ismslib-2.1.dist-info/LICENSE
ismslib-2.1.dist-info/METADATA
ismslib-2.1.dist-info/WHEEL
ismslib-2.1.dist-info/top_level.txt
ismslib-2.1.dist-info/RECORD
