Metadata-Version: 2.1
Name: ismslib
Version: 2.1
Summary: Very simple and easy to use library for integrating SSLWireless SMS API.
Home-page: https://github.com/rkbi/ismslib.py
Author: Rakibul Islam
Author-email: rkbssl@outlook.com
License: GPLv3
Keywords: sslwireless,sms,isms,ismslib,official,api
Platform: UNKNOWN
Classifier: Programming Language :: Python :: 3
Classifier: Operating System :: OS Independent
Classifier: Intended Audience :: Developers
Requires-Python: >=3.6
Requires-Dist: requests
Requires-Dist: xmltodict
